malurl/__init__.py
malurl/malurl.py
malurl-1.0.2.dist-info/LICENSE
malurl-1.0.2.dist-info/METADATA
malurl-1.0.2.dist-info/WHEEL
malurl-1.0.2.dist-info/top_level.txt
malurl-1.0.2.dist-info/RECORD
